LICENSE.txt
MANIFEST.in
README.md
setup.cfg
setup.py
bricklink/__init__.py
bricklink/api.py
bricklink/authhandler.py
bricklink/config.py
bricklink/utils.py
bricklink/constants/constants.py
bricklink/constants/errors.py
bricklink/endpoints/__init__.py
bricklink/endpoints/base.py
bricklink/endpoints/orders.py
bricklink/models/__init__.py
bricklink/models/base.py
bricklink/models/errors.py
bricklink/models/orders.py
python_bricklink_api.egg-info/PKG-INFO
python_bricklink_api.egg-info/SOURCES.txt
python_bricklink_api.egg-info/dependency_links.txt
python_bricklink_api.egg-info/requires.txt
python_bricklink_api.egg-info/top_level.txt